<annotation>
	<folder>train</folder>
	<filename>92.jpg</filename>
	<path>C:\Users\difra\object_detection_demo\data\images\train\92.jpg</path>
	<source>
		<database>Unknown</database>
	</source>
	<size>
		<width>1280</width>
		<height>720</height>
		<depth>3</depth>
	</size>
	<segmented>0</segmented>
	<object>
		<name>truck</name>
		<pose>Unspecified</pose>
		<truncated>1</truncated>
		<difficult>0</difficult>
		<bndbox>
			<xmin>33</xmin>
			<ymin>287</ymin>
			<xmax>754</xmax>
			<ymax>720</ymax>
		</bndbox>
	</object>
	<object>
		<name>car</name>
		<pose>Unspecified</pose>
		<truncated>0</truncated>
		<difficult>0</difficult>
		<bndbox>
			<xmin>1017</xmin>
			<ymin>220</ymin>
			<xmax>1095</xmax>
			<ymax>300</ymax>
		</bndbox>
	</object>
	<object>
		<name>car</name>
		<pose>Unspecified</pose>
		<truncated>0</truncated>
		<difficult>0</difficult>
		<bndbox>
			<xmin>937</xmin>
			<ymin>201</ymin>
			<xmax>1006</xmax>
			<ymax>260</ymax>
		</bndbox>
	</object>
	<object>
		<name>traffic light</name>
		<pose>Unspecified</pose>
		<truncated>0</truncated>
		<difficult>0</difficult>
		<bndbox>
			<xmin>973</xmin>
			<ymin>11</ymin>
			<xmax>1111</xmax>
			<ymax>42</ymax>
		</bndbox>
	</object>
</annotation>
